odoo/addons/base_import_default_enable_tracking/README.rst
odoo/addons/base_import_default_enable_tracking/__init__.py
odoo/addons/base_import_default_enable_tracking/__manifest__.py
odoo/addons/base_import_default_enable_tracking/i18n/base_import_default_enable_tracking.pot
odoo/addons/base_import_default_enable_tracking/i18n/es.po
odoo/addons/base_import_default_enable_tracking/i18n/hr.po
odoo/addons/base_import_default_enable_tracking/i18n/it.po
odoo/addons/base_import_default_enable_tracking/readme/DESCRIPTION.rst
odoo/addons/base_import_default_enable_tracking/static/description/icon.png
odoo/addons/base_import_default_enable_tracking/static/description/index.html
odoo/addons/base_import_default_enable_tracking/static/src/xml/base_import.xml
odoo_addon_base_import_default_enable_tracking-16.0.1.0.0.2.dist-info/METADATA
odoo_addon_base_import_default_enable_tracking-16.0.1.0.0.2.dist-info/WHEEL
odoo_addon_base_import_default_enable_tracking-16.0.1.0.0.2.dist-info/top_level.txt
odoo_addon_base_import_default_enable_tracking-16.0.1.0.0.2.dist-info/RECORD
